{
  "system": {
    "cpu": "AMD Ryzen 9 9950X 16-Core Processor",
    "memory_gb": 61,
    "os": "Windows"
  },
  "gpu": {
    "name": "NVIDIA GeForce RTX 5080",
    "backend": "d3d12",
    "driver": "D3D12 driver version 32.0.15.9144"
  },
  "model": {
    "name": "lfm2_moe",
    "path": "e:/workspace/project/test/ai-models/lfm2-8b-a1b/webgpu/model_q4f16.onnx",
    "format": "onnx_generic",
    "layers": 24,
    "hidden_size": 2048,
    "vocab_size": 65536
  },
  "benchmark": {
    "decode_tokens": 128,
    "results": [
      {
        "input_tokens": 128,
        "prefill_ms": 1348.5,
        "prefill_tok_s": 94.9,
        "decode_ms": 1758.4,
        "decode_tok_s": 72.8
      },
      {
        "input_tokens": 256,
        "prefill_ms": 263.3,
        "prefill_tok_s": 972.2,
        "decode_ms": 1980.3,
        "decode_tok_s": 64.6
      },
      {
        "input_tokens": 512,
        "prefill_ms": 523.3,
        "prefill_tok_s": 978.4,
        "decode_ms": 2422.4,
        "decode_tok_s": 52.8
      },
      {
        "input_tokens": 1024,
        "prefill_ms": 1046.5,
        "prefill_tok_s": 978.5,
        "decode_ms": 3273.2,
        "decode_tok_s": 39.1
      },
      {
        "input_tokens": 2048,
        "prefill_ms": 2912.2,
        "prefill_tok_s": 703.3,
        "decode_ms": 4942.9,
        "decode_tok_s": 25.9
      },
      {
        "input_tokens": 4096,
        "prefill_ms": 9856.5,
        "prefill_tok_s": 415.6,
        "decode_ms": 8328.4,
        "decode_tok_s": 15.4
      }
    ]
  },
  "timestamp": "2026-03-29T23:10:40"
}
